amano/__init__.py
amano/attribute.py
amano/attributemapping.py
amano/base_attribute.py
amano/condition.py
amano/constants.py
amano/cursor.py
amano/errors.py
amano/index.py
amano/item.py
amano/table.py
amano/table_schema.py
amano/undefined.py
amano/utils.py
amano-0.2.0.dist-info/LICENSE
amano-0.2.0.dist-info/WHEEL
amano-0.2.0.dist-info/METADATA
amano-0.2.0.dist-info/RECORD
